cn_font_split/__init__.py
cn_font_split/cli.py
cn_font_split/font_split.py
cn_font_split/gen/__init__.py
cn_font_split/gen/index_pb2.py
cn_font_split/gen/init.ps1
cn_font_split/gen/init.sh
cn_font_split/gen/services_pb2.py
cn_font_split-7.1.0.dist-info/METADATA
cn_font_split-7.1.0.dist-info/WHEEL
cn_font_split-7.1.0.dist-info/entry_points.txt
cn_font_split-7.1.0.dist-info/top_level.txt
cn_font_split-7.1.0.dist-info/RECORD
